arpeggio/__init__.py
arpeggio/cleanpeg.py
arpeggio/export.py
arpeggio/peg.py
arpeggio/utils.py
arpeggio/tests/__init__.py
arpeggio/tests/test_decorator_combine.py
arpeggio/tests/test_default_semantic_action.py
arpeggio/tests/test_eolterm.py
arpeggio/tests/test_error_reporting.py
arpeggio/tests/test_examples.py
arpeggio/tests/test_exporter.py
arpeggio/tests/test_flags.py
arpeggio/tests/test_parser_params.py
arpeggio/tests/test_parser_resilience.py
arpeggio/tests/test_parsing_expressions.py
arpeggio/tests/test_peg_parser.py
arpeggio/tests/test_position.py
arpeggio/tests/test_ptnode_navigation_expressions.py
arpeggio/tests/test_python_parser.py
arpeggio/tests/test_reduce_tree.py
arpeggio/tests/test_semantic_action_results.py
arpeggio/tests/test_separators.py
arpeggio/tests/test_sequence_params.py
arpeggio/tests/test_suppression.py
arpeggio/tests/test_unicode.py
arpeggio/tests/test_visitor.py
arpeggio/tests/regressions/__init__.py
arpeggio/tests/regressions/test_direct_rule_call.py
arpeggio/tests/regressions/test_memoization.py
arpeggio/tests/regressions/issue_16/__init__.py
arpeggio/tests/regressions/issue_16/test_issue_16.py
arpeggio/tests/regressions/issue_20/__init__.py
arpeggio/tests/regressions/issue_20/test_issue_20.py
arpeggio/tests/regressions/issue_22/__init__.py
arpeggio/tests/regressions/issue_22/grammar1.peg
arpeggio/tests/regressions/issue_22/grammar2.peg
arpeggio/tests/regressions/issue_22/test_issue_22.py
arpeggio/tests/regressions/issue_26/__init__.py
arpeggio/tests/regressions/issue_26/test_issue_26.py
arpeggio/tests/regressions/issue_31/__init__.py
arpeggio/tests/regressions/issue_31/test_issue_31.py
arpeggio/tests/regressions/issue_32/__init__.py
arpeggio/tests/regressions/issue_32/test_issue_32.py
arpeggio/tests/regressions/issue_43/__init__.py
arpeggio/tests/regressions/issue_43/test_issue43.py
arpeggio/tests/regressions/issue_61/test_issue_61.py
arpeggio/tests/regressions/issue_73/test_issue_73.py
Arpeggio-2.0.3.dist-info/AUTHORS.md
Arpeggio-2.0.3.dist-info/LICENSE
Arpeggio-2.0.3.dist-info/METADATA
Arpeggio-2.0.3.dist-info/WHEEL
Arpeggio-2.0.3.dist-info/top_level.txt
Arpeggio-2.0.3.dist-info/RECORD
