Metadata-Version: 2.1
Name: Arpeggio
Version: 2.0.3
Summary: Packrat parser interpreter
Home-page: https://github.com/textX/Arpeggio
Download-URL: 
Author: Igor R. Dejanovic
Author-email: igor.dejanovic@gmail.com
License: MIT
Keywords: parser,PEG,packrat,library,interpreter
Classifier: Development Status :: 5 - Production/Stable
Classifier: Intended Audience :: Developers
Classifier: Intended Audience :: Information Technology
Classifier: Intended Audience :: Science/Research
Classifier: Topic :: Software Development :: Interpreters
Classifier: Topic :: Software Development :: Compilers
Classifier: Topic :: Software Development :: Libraries :: Python Modules
Classifier: License :: OSI Approved :: MIT License
Classifier: Operating System :: OS Independent
Classifier: Programming Language :: Python :: 3
Classifier: Programming Language :: Python :: 3.6
Classifier: Programming Language :: Python :: 3.7
Classifier: Programming Language :: Python :: 3.8
Classifier: Programming Language :: Python :: 3.9
Classifier: Programming Language :: Python :: 3.10
Provides-Extra: dev
Provides-Extra: test
License-File: LICENSE
License-File: AUTHORS.md
